subprocplus/README.MD
subprocplus/__init__.py
subprocplus/requirements.txt
subprocplus/subproc.py
subprocplus/thirdparty.json
subprocplus/utilities.py
subprocplus/data/README.md
subprocplus/data/windows_syscalls.db
subprocplus/datatypes/__init__.py
subprocplus/datatypes/common.py
subprocplus/datatypes/elf.py
subprocplus/datatypes/windows/__init__.py
subprocplus/datatypes/windows/_enums.py
subprocplus/datatypes/windows/_net.py
subprocplus/datatypes/windows/_scalars.py
subprocplus/datatypes/windows/ntstatus.py
subprocplus/datatypes/windows/wingdi.py
subprocplus/exploit/__init__.py
subprocplus/exploit/windows.py
subprocplus/proc/__init__.py
subprocplus/proc/linux.py
subprocplus/proc/native.py
subprocplus/proc/windows.py
subprocplus/windll/__init__.py
subprocplus/windll/advapi32.py
subprocplus/windll/bcrypt.py
subprocplus/windll/gdi32.py
subprocplus/windll/iphlpapi.py
subprocplus/windll/kernel32.py
subprocplus/windll/ntdll.py
subprocplus/windll/psapi.py
subprocplus/windll/user32.py
subprocplus-0.10.dist-info/LICENSE.rst
subprocplus-0.10.dist-info/METADATA
subprocplus-0.10.dist-info/WHEEL
subprocplus-0.10.dist-info/top_level.txt
subprocplus-0.10.dist-info/RECORD
