Metadata-Version: 2.1
Name: subprocplus
Version: 0.10
Summary: subprocess + some useful stuff
Home-page: https://github.com/hansalemaos/subprocplus
Author: Johannes Fischer
Author-email: aulasparticularesdealemaosp@gmail.com
License: MIT
Keywords: subprocess
Classifier: Development Status :: 4 - Beta
Classifier: Programming Language :: Python :: 3 :: Only
Classifier: Programming Language :: Python :: 3.10
Classifier: Topic :: Software Development :: Libraries :: Python Modules
Classifier: Topic :: Utilities
License-File: LICENSE.rst
Requires-Dist: boltons
Requires-Dist: procciao
Requires-Dist: rlogfi
Requires-Dist: touchtouch
